{
	"name": "DS_Save_Json_output",
	"properties": {
		"linkedServiceName": {
			"referenceName": "AzureBlobStorage1",
			"type": "LinkedServiceReference"
		},
		"parameters": {
			"pTargetfilename": {
				"type": "string"
			}
		},
		"annotations": [],
		"type": "DelimitedText",
		"typeProperties": {
			"location": {
				"type": "AzureBlobStorageLocation",
				"folderPath": "Target_dir",
				"container": "samplesfiles"
			},
			"columnDelimiter": ",",
			"escapeChar": "\\",
			"firstRowAsHeader": false,
			"quoteChar": "\""
		},
		"schema": [
			{
				"type": "String"
			},
			{
				"type": "String"
			},
			{
				"type": "String"
			},
			{
				"type": "String"
			}
		]
	}
}